setup.py
jcdb/__init__.py
jcdb.egg-info/PKG-INFO
jcdb.egg-info/SOURCES.txt
jcdb.egg-info/dependency_links.txt
jcdb.egg-info/entry_points.txt
jcdb.egg-info/not-zip-safe
jcdb.egg-info/requires.txt
jcdb.egg-info/top_level.txt
jcdb/core/__init__.py
jcdb/core/object.py
jcdb/tests/__init__.py
jcdb/tests/core/__init__.py
jcdb/tests/core/inheritance.py
jcdb/tests/core/object.py