Metadata-Version: 1.1
Name: jcdb
Version: 0.1.0
Summary: The JSON-Class Database.
Home-page: http://github.com/finnmglas/jcdb
Author: Finn M Glas
Author-email: finn@finnmglas.com
License: MIT
Keywords: database json
Platform: UNKNOWN
Classifier: Development Status :: 1 - Planning
Classifier: License :: OSI Approved :: MIT License
Classifier: Programming Language :: Python :: 3
